{"Version":"1.0.0.0","LastState":11,"Modules":[{"IsEncoderOffsetConfigured":true,"IsDeviceSelectionCompleted":true,"IsConfigurationCompleted":true,"ModuleName":"Front Left","ModuleId":0,"Encoder":{"Id":9,"Name":"FL Encoder","Model":"CANCoder vers. H","CANbus":"rio","CANbusFriendly":""},"SteerMotor":{"Id":4,"Name":"SWERVE FL STEER","Model":"Talon FX","CANbus":"rio","CANbusFriendly":""},"DriveMotor":{"Id":3,"Name":"SWERVE FL DRIVE","Model":"Talon FX","CANbus":"rio","CANbusFriendly":""},"EncoderOffset":-0.964599609375,"DriveMotorSelectionState":1,"SteerMotorSelectionState":1,"SteerEncoderSelectionState":1},{"IsEncoderOffsetConfigured":true,"IsDeviceSelectionCompleted":true,"IsConfigurationCompleted":true,"ModuleName":"Front Right","ModuleId":1,"Encoder":{"Id":12,"Name":"FR Encoder","Model":"CANCoder vers. H","CANbus":"rio","CANbusFriendly":""},"SteerMotor":{"Id":2,"Name":"SWERVE FR STEER","Model":"Talon FX","CANbus":"rio","CANbusFriendly":""},"DriveMotor":{"Id":1,"Name":"SWERVE FR DRIVE","Model":"Talon FX","CANbus":"rio","CANbusFriendly":""},"EncoderOffset":-0.498046875,"DriveMotorSelectionState":1,"SteerMotorSelectionState":1,"SteerEncoderSelectionState":1},{"IsEncoderOffsetConfigured":true,"IsDeviceSelectionCompleted":true,"IsConfigurationCompleted":true,"ModuleName":"Back Left","ModuleId":2,"Encoder":{"Id":10,"Name":"BL Encoder","Model":"CANCoder vers. H","CANbus":"rio","CANbusFriendly":""},"SteerMotor":{"Id":6,"Name":"SWERVE BL STEER","Model":"Talon FX","CANbus":"rio","CANbusFriendly":""},"DriveMotor":{"Id":5,"Name":"SWERVE BL DRIVE","Model":"Talon FX","CANbus":"rio","CANbusFriendly":""},"EncoderOffset":-0.025634765625,"DriveMotorSelectionState":1,"SteerMotorSelectionState":1,"SteerEncoderSelectionState":1},{"IsEncoderOffsetConfigured":true,"IsDeviceSelectionCompleted":true,"IsConfigurationCompleted":true,"ModuleName":"Back Right","ModuleId":3,"Encoder":{"Id":11,"Name":"BR Encoder","Model":"CANCoder vers. H","CANbus":"rio","CANbusFriendly":""},"SteerMotor":{"Id":8,"Name":"SWERVE BR STEER","Model":"Talon FX","CANbus":"rio","CANbusFriendly":""},"DriveMotor":{"Id":7,"Name":"SWERVE BR DRIVE","Model":"Talon FX","CANbus":"rio","CANbusFriendly":""},"EncoderOffset":-0.09912109375,"DriveMotorSelectionState":1,"SteerMotorSelectionState":1,"SteerEncoderSelectionState":1}],"SwerveOptions":{"IsValidConfiguration":true,"Gyro":{"Id":0,"Name":"Pigeon 2 (Device ID 0)","Model":"Pigeon 2","CANbus":"rio","CANbusFriendly":""},"VerticalTrackSizeInches":23.5,"HorizontalTrackSizeInches":17.0,"WheelRadiusInches":2.0,"IsLeftSideInverted":false,"IsRightSideInverted":true,"SwerveModuleType":3,"SwerveModuleConfiguration":{"_CouplingRatio":3.5714285714285716,"_CustomName":"L2","SteerRatio":12.8,"Flipped":3,"DriveRatio":6.746031746031747,"CouplingRatio":3.5714285714285716,"CustomName":"L2"},"HasVerifiedSteer":true,"HasVerifiedDrive":true,"IsSteerMotorReversed":false}}